[
  {
    "full_name": "nworiekingslee/Open-pomodoro",
    "stargazers_count": 0,
    "open_issues_count": 0,
    "forks_count": 1
  },
  {
    "full_name": "rajivranjanmars/readme",
    "stargazers_count": 17,
    "open_issues_count": 5,
    "forks_count": 18
  },
  {
    "full_name": "firstcontributions/first-contributions",
    "stargazers_count": 33924,
    "open_issues_count": 257,
    "forks_count": 60380
  },
  {
    "full_name": "open-sauced/open-sauced",
    "stargazers_count": 881,
    "open_issues_count": 0,
    "forks_count": 633
  }
]